more_bisect.py
more_bisect-0.1.1.dist-info/LICENSE
more_bisect-0.1.1.dist-info/METADATA
more_bisect-0.1.1.dist-info/WHEEL
more_bisect-0.1.1.dist-info/top_level.txt
more_bisect-0.1.1.dist-info/RECORD
