Metadata-Version: 2.1
Name: more-bisect
Version: 0.1.1
Summary: A binary search extension of Python `bisect` module that enables flexible comparisons.
Author: Kaiwen Wu
Author-email: kps6326@hotmail.com
License: MIT
Keywords: bisect
Platform: UNKNOWN
Classifier: License :: OSI Approved :: MIT License
Classifier: Programming Language :: Python :: 2.7
Classifier: Programming Language :: Python :: 3
Requires-Python: >=2.7
License-File: LICENSE
